ji_project_util/__init__.py
ji_project_util/log/LogIdFilter.py
ji_project_util/log/LogIdManager.py
ji_project_util/log/LogManager.py
ji_project_util/log/__init__.py
ji_project_util/log/logging.yaml
ji_project_util/monitor/Monitor.py
ji_project_util/monitor/MonitorModel.py
ji_project_util/monitor/MonitorThreadLocal.py
ji_project_util/monitor/__init__.py
ji_project_util-0.0.7.dist-info/LICENSE
ji_project_util-0.0.7.dist-info/METADATA
ji_project_util-0.0.7.dist-info/WHEEL
ji_project_util-0.0.7.dist-info/top_level.txt
ji_project_util-0.0.7.dist-info/RECORD
